testgear/__init__.py
testgear/base_classes.py
testgear/Fluke/F5440B.py
testgear/Fluke/__init__.py
testgear/HPAK/HP3458A.py
testgear/HPAK/HP3488A.py
testgear/HPAK/__init__.py
testgear/Keithley/K182.py
testgear/Keithley/__init__.py
testgear/Knick/JS3010.py
testgear/Knick/__init__.py
testgear/LakeShore/__init__.py
testgear-0.0.1.dist-info/LICENSE
testgear-0.0.1.dist-info/METADATA
testgear-0.0.1.dist-info/WHEEL
testgear-0.0.1.dist-info/top_level.txt
testgear-0.0.1.dist-info/RECORD
